Metadata-Version: 2.1
Name: yandex-webmaster-api
Version: 0.0.2
Summary: wrapper for yandex webmaster api
Home-page: https://github.com/bzdvdn/yandex-webmaster-api
Author: bzdvdn
Author-email: bzdv.dn@gmail.com
License: MIT
Requires-Python: >=3.7
Requires-Dist: requests
